click_mcp/__init__.py
click_mcp/decorator.py
click_mcp/scanner.py
click_mcp/server.py
click_mcp-0.5.0.dist-info/METADATA
click_mcp-0.5.0.dist-info/WHEEL
click_mcp-0.5.0.dist-info/licenses/LICENSE
click_mcp-0.5.0.dist-info/RECORD
