Metadata-Version: 2.4
Name: click-mcp
Version: 0.5.0
Summary: Extend Click applications with Model Context Protocol (MCP) support
Project-URL: Homepage, https://github.com/crowecawcaw/click-mcp
Project-URL: Issues, https://github.com/crowecawcaw/click-mcp/issues
Author: Stephen Crowe
License-Expression: MIT
License-File: LICENSE
Classifier: Development Status :: 4 - Beta
Classifier: Intended Audience :: Developers
Classifier: Operating System :: OS Independent
Classifier: Programming Language :: Python :: 3
Classifier: Programming Language :: Python :: 3.10
Classifier: Programming Language :: Python :: 3.11
Classifier: Programming Language :: Python :: 3.12
Classifier: Programming Language :: Python :: 3.13
Requires-Python: >=3.10
Requires-Dist: click>=7.0
Requires-Dist: mcp>=0.1.0
Provides-Extra: test
Requires-Dist: pytest-anyio; extra == 'test'
Requires-Dist: pytest-cov; extra == 'test'
Requires-Dist: pytest>=6.0; extra == 'test'
Requires-Dist: trio; extra == 'test'
